{
    "name": "facturascripts/facturascripts_2015",
    "description": "Software de facturación y contabilidad para pymes, fácil, libre y con actualizaciones constantes.",
    "authors": [
        {
            "name": "Carlos García Gómez",
            "email": "neorazorx@gmail.com"
        }
    ],
    "require": {
        "php": ">=5.4",
        "phpmailer/phpmailer": "v5.*",
        "components/jquery": "v3.*",
        "components/font-awesome": "v4.*",
        "mk-j/php_xlsxwriter": "v0.37",
        "twbs/bootstrap": "v3.*",
        "thomaspark/bootswatch": "v3.*",
        "makeusabrew/bootbox": "v4.x-dev"
    },
    "require-dev": {
        "tecnickcom/tcpdf": "^6.2",
        "phpunit/phpunit": "^5.7",
        "doctrine/instantiator": "^1.0.0",
        "dompdf/dompdf": "^0.8.0",
        "mpdf/mpdf": "^7.0.0",
        "jpgraph/jpgraph": "^4.0",
        "friendsofphp/php-cs-fixer": "@stable",
        "phpcompatibility/php-compatibility": "^8.0",
        "squizlabs/php_codesniffer": "^3.3"
    },
    "suggest": {
        "mpdf/mpdf": "Option for rendering PDF with PDF Writer",
        "dompdf/dompdf": "Option for rendering PDF with PDF Writer",
        "tecnickcom/tcpdf": "Option for rendering PDF with PDF Writer",
        "jpgraph/jpgraph": "Option for rendering charts, or including charts with PDF or HTML Writers"
    },
    "autoload": {
        "psr-4": {
            "PhpOffice\\PhpSpreadsheet\\": "src/PhpSpreadsheet"
        }
    },
    "autoload-dev": {
        "psr-4": {
            "PhpOffice\\PhpSpreadsheetTests\\": "tests/PhpSpreadsheetTests"
        }
    }
}
